{
  "indexes": [
    {
      "collectionGroup": "chatSessions",
      "queryScope": "COLLECTION",
      "fields": [
        { "fieldPath": "visitorId", "order": "ASCENDING" },
        { "fieldPath": "createdAt", "order": "DESCENDING" }
      ]
    },
    {
      "collectionGroup": "chatSessions",
      "queryScope": "COLLECTION",
      "fields": [
        { "fieldPath": "status", "order": "ASCENDING" },
        { "fieldPath": "createdAt", "order": "DESCENDING" }
      ]
    },
    {
      "collectionGroup": "chatSessions",
      "queryScope": "COLLECTION",
      "fields": [
        { "fieldPath": "escalated", "order": "ASCENDING" },
        { "fieldPath": "createdAt", "order": "DESCENDING" }
      ]
    },
    {
      "collectionGroup": "messages",
      "queryScope": "COLLECTION",
      "fields": [
        { "fieldPath": "createdAt", "order": "ASCENDING" }
      ]
    },
    {
      "collectionGroup": "purchases",
      "queryScope": "COLLECTION",
      "fields": [
        { "fieldPath": "uid", "order": "ASCENDING" },
        { "fieldPath": "createdAt", "order": "DESCENDING" }
      ]
    },
    {
      "collectionGroup": "esimStatuses",
      "queryScope": "COLLECTION",
      "fields": [
        { "fieldPath": "uid", "order": "ASCENDING" }
      ]
    },
    {
      "collectionGroup": "surveys",
      "queryScope": "COLLECTION",
      "fields": [
        { "fieldPath": "createdAt", "order": "DESCENDING" }
      ]
    },
    {
      "collectionGroup": "chatSessions",
      "queryScope": "COLLECTION",
      "fields": [
        { "fieldPath": "scheduledDeleteAt", "order": "ASCENDING" }
      ]
    }
  ],
  "fieldOverrides": [
    {
      "collectionGroup": "ragDocuments",
      "fieldPath": "embedding",
      "indexes": [
        {
          "order": "__UNSET__",
          "queryScope": "COLLECTION",
          "vectorConfig": {
            "dimension": 768,
            "flat": {}
          }
        }
      ]
    }
  ]
}
